billingio/__init__.py
billingio/_http.py
billingio/client.py
billingio/errors.py
billingio/pagination.py
billingio/types.py
billingio/webhooks.py
billingio-1.0.0.dist-info/METADATA
billingio-1.0.0.dist-info/WHEEL
billingio-1.0.0.dist-info/top_level.txt
billingio-1.0.0.dist-info/RECORD
