Metadata-Version: 2.4
Name: billingio
Version: 1.0.0
Summary: Official Python SDK for the billing.io crypto checkout API
Author-email: "billing.io" <support@billing.io>
License: Proprietary
Project-URL: Homepage, https://billing.io
Project-URL: Documentation, https://docs.billing.io
Project-URL: Repository, https://github.com/billingio/billingio-python
Keywords: billing,crypto,payments,checkout,stablecoin
Classifier: Development Status :: 5 - Production/Stable
Classifier: Intended Audience :: Developers
Classifier: Programming Language :: Python :: 3
Classifier: Programming Language :: Python :: 3.9
Classifier: Programming Language :: Python :: 3.10
Classifier: Programming Language :: Python :: 3.11
Classifier: Programming Language :: Python :: 3.12
Classifier: Programming Language :: Python :: 3.13
Classifier: Topic :: Software Development :: Libraries :: Python Modules
Classifier: Typing :: Typed
Requires-Python: >=3.9
Requires-Dist: requests>=2.28
